{
  "0": "Summer Intern",
  "1": "Summer Intern",
  "2": "Intern",
  "3": "Intern",
  "4": "Intern",
  "5": "Junior Analyst",
  "6": "Analyst",
  "7": "Analyst",
  "8": "Senior Analyst",
  "9": "Senior Analyst",
  "10": "Junior Associate",
  "11": "Associate",
  "12": "Associate",
  "13": "Associate",
  "14": "Associate",
  "15": "Associate",
  "16": "Associate",
  "17": "Senior Associate",
  "18": "Senior Associate",
  "19": "Senior Associate",
  "20": "Vice President",
  "21": "Vice President",
  "22": "Vice President",
  "23": "Vice President",
  "24": "Vice President",
  "25": "Vice President",
  "26": "Vice President",
  "27": "Vice President",
  "28": "Vice President",
  "29": "Vice President",
  "30": "Senior Vice President",
  "31": "Senior Vice President",
  "32": "Senior Vice President",
  "33": "Senior Vice President",
  "34": "Senior Vice President",
  "35": "Senior Vice President",
  "36": "Senior Vice President",
  "37": "Senior Vice President",
  "38": "Senior Vice President",
  "39": "Senior Vice President",
  "40": "Director",
  "41": "Director",
  "42": "Director",
  "43": "Director",
  "44": "Director",
  "45": "Director",
  "46": "Director",
  "47": "Director",
  "48": "Director",
  "49": "Director",
  "50": "Managing Director",
  "51": "Managing Director",
  "52": "Managing Director",
  "53": "Managing Director",
  "54": "Managing Director",
  "55": "Managing Director",
  "56": "Managing Director",
  "57": "Managing Director",
  "58": "Managing Director",
  "59": "Managing Director",
  "60": "Senior Managing Director",
  "61": "Senior Managing Director",
  "62": "Senior Managing Director",
  "63": "Senior Managing Director",
  "64": "Senior Managing Director",
  "65": "Group Head",
  "66": "Group Head",
  "67": "Group Head",
  "68": "COO",
  "69": "CEO (nice!)"
}
